unzer/__init__.py
unzer/client.py
unzer/utils.py
unzer/model/__init__.py
unzer/model/additional_transaction_data.py
unzer/model/address.py
unzer/model/base.py
unzer/model/basket.py
unzer/model/basketItem.py
unzer/model/customer.py
unzer/model/error.py
unzer/model/payment.py
unzer/model/paymentpage.py
unzer/model/webhook.py
unzer/model/payment_type/__init__.py
unzer/model/payment_type/abstract_paymenttype.py
unzer/model/payment_type/applepay.py
unzer/model/payment_type/bancontact.py
unzer/model/payment_type/card.py
unzer/model/payment_type/googlepay.py
unzer/model/payment_type/ideal.py
unzer/model/payment_type/paylater_invoice.py
unzer/model/payment_type/paypal.py
unzer/model/payment_type/sofort.py
unzer-1.3.0.dist-info/licenses/LICENSE
unzer-1.3.0.dist-info/METADATA
unzer-1.3.0.dist-info/WHEEL
unzer-1.3.0.dist-info/top_level.txt
unzer-1.3.0.dist-info/RECORD
