Metadata-Version: 2.4
Name: unzer
Version: 1.3.0
Summary: An unofficial python SDK for unzer.com
Author-email: Sven Eberth <se@mausbrand.de>
Maintainer-email: Sven Eberth <se@mausbrand.de>
License: MIT License
Project-URL: Repository, https://github.com/mausbrand/unzer-python-sdk.git
Project-URL: Bug Tracker, https://github.com/mausbrand/unzer-python-sdk/issues
Project-URL: Changelog, https://github.com/mausbrand/unzer-python-sdk/releases
Keywords: unzer,payment,sdk,client
Classifier: Intended Audience :: Developers
Classifier: License :: OSI Approved :: MIT License
Classifier: Operating System :: OS Independent
Classifier: Programming Language :: Python :: 3.10
Classifier: Programming Language :: Python :: 3.11
Classifier: Programming Language :: Python :: 3.12
Classifier: Programming Language :: Python :: 3.13
Classifier: Topic :: Software Development :: Libraries :: Python Modules
Requires-Python: >=3.10
License-File: LICENSE
Requires-Dist: requests
Dynamic: license-file
